{
  "metadata": {
    "project_id": "RSI-TRACKER-V1.5-LOG-012",
    "engineer": "Admin_Sensor_Lab",
    "environment": "Obstructed_Office",
    "noise_floor": -98.2
  },
  "points": [
    {
      "point_id": "P12_00",
      "ground_truth_m": 3.31,
      "readings": [
        {
          "ssid": "Bracket_Anchor_A",
          "bssid": "00:1A:2B:3C:4D:5E",
          "rssi": -55.57,
          "std_dev": 2.93,
          "anomaly_flag": "None"
        },
        {
          "ssid": "Bracket_Anchor_B",
          "bssid": "00:1A:2B:3C:4D:5F",
          "rssi": -54.95,
          "std_dev": 1.33,
          "anomaly_flag": "None"
        },
        {
          "ssid": "Bracket_Anchor_C",
          "bssid": "00:1A:2B:3C:4D:60",
          "rssi": -56.47,
          "std_dev": 3.81,
          "anomaly_flag": "None"
        }
      ]
    },
    {
      "point_id": "P12_01",
      "ground_truth_m": 5.12,
      "readings": [
        {
          "ssid": "Bracket_Anchor_A",
          "bssid": "00:1A:2B:3C:4D:5E",
          "rssi": -63.43,
          "std_dev": 2.13,
          "anomaly_flag": "None"
        },
        {
          "ssid": "Bracket_Anchor_B",
          "bssid": "00:1A:2B:3C:4D:5F",
          "rssi": -61.96,
          "std_dev": 3.93,
          "anomaly_flag": "None"
        },
        {
          "ssid": "Bracket_Anchor_C",
          "bssid": "00:1A:2B:3C:4D:60",
          "rssi": -65.62,
          "std_dev": 0.89,
          "anomaly_flag": "None"
        }
      ]
    },
    {
      "point_id": "P12_02",
      "ground_truth_m": 2.69,
      "readings": [
        {
          "ssid": "Bracket_Anchor_A",
          "bssid": "00:1A:2B:3C:4D:5E",
          "rssi": -115,
          "std_dev": 0.8,
          "anomaly_flag": "SIGNAL_SHADOWING"
        },
        {
          "ssid": "Bracket_Anchor_B",
          "bssid": "00:1A:2B:3C:4D:5F",
          "rssi": -51.47,
          "std_dev": 3.35,
          "anomaly_flag": "None"
        },
        {
          "ssid": "Bracket_Anchor_C",
          "bssid": "00:1A:2B:3C:4D:60",
          "rssi": -53.4,
          "std_dev": 0.75,
          "anomaly_flag": "None"
        }
      ]
    },
    {
      "point_id": "P12_03",
      "ground_truth_m": 4.97,
      "readings": [
        {
          "ssid": "Bracket_Anchor_A",
          "bssid": "00:1A:2B:3C:4D:5E",
          "rssi": -60.46,
          "std_dev": 2.14,
          "anomaly_flag": "None"
        },
        {
          "ssid": "Bracket_Anchor_B",
          "bssid": "00:1A:2B:3C:4D:5F",
          "rssi": -63.54,
          "std_dev": 2.54,
          "anomaly_flag": "None"
        },
        {
          "ssid": "Bracket_Anchor_C",
          "bssid": "00:1A:2B:3C:4D:60",
          "rssi": -61.45,
          "std_dev": 2.04,
          "anomaly_flag": "None"
        }
      ]
    },
    {
      "point_id": "P12_04",
      "ground_truth_m": 3.55,
      "readings": [
        {
          "ssid": "Bracket_Anchor_A",
          "bssid": "00:1A:2B:3C:4D:5E",
          "rssi": -53.39,
          "std_dev": 0.84,
          "anomaly_flag": "None"
        },
        {
          "ssid": "Bracket_Anchor_B",
          "bssid": "00:1A:2B:3C:4D:5F",
          "rssi": -55.43,
          "std_dev": 1.39,
          "anomaly_flag": "None"
        },
        {
          "ssid": "Bracket_Anchor_C",
          "bssid": "00:1A:2B:3C:4D:60",
          "rssi": -53.93,
          "std_dev": 3.17,
          "anomaly_flag": "None"
        }
      ]
    },
    {
      "point_id": "P12_05",
      "ground_truth_m": 2.66,
      "readings": [
        {
          "ssid": "Bracket_Anchor_A",
          "bssid": "00:1A:2B:3C:4D:5E",
          "rssi": -50.59,
          "std_dev": 2.01,
          "anomaly_flag": "None"
        },
        {
          "ssid": "Bracket_Anchor_B",
          "bssid": "00:1A:2B:3C:4D:5F",
          "rssi": -54.83,
          "std_dev": 1.25,
          "anomaly_flag": "None"
        },
        {
          "ssid": "Bracket_Anchor_C",
          "bssid": "00:1A:2B:3C:4D:60",
          "rssi": -54.75,
          "std_dev": 3.2,
          "anomaly_flag": "None"
        }
      ]
    },
    {
      "point_id": "P12_06",
      "ground_truth_m": 5.13,
      "readings": [
        {
          "ssid": "Bracket_Anchor_A",
          "bssid": "00:1A:2B:3C:4D:5E",
          "rssi": -58.86,
          "std_dev": 3.82,
          "anomaly_flag": "None"
        },
        {
          "ssid": "Bracket_Anchor_B",
          "bssid": "00:1A:2B:3C:4D:5F",
          "rssi": -58.34,
          "std_dev": 2.05,
          "anomaly_flag": "None"
        },
        {
          "ssid": "Bracket_Anchor_C",
          "bssid": "00:1A:2B:3C:4D:60",
          "rssi": -58.46,
          "std_dev": 3.81,
          "anomaly_flag": "None"
        }
      ]
    },
    {
      "point_id": "P12_07",
      "ground_truth_m": 2.76,
      "readings": [
        {
          "ssid": "Bracket_Anchor_A",
          "bssid": "00:1A:2B:3C:4D:5E",
          "rssi": -55.96,
          "std_dev": 0.99,
          "anomaly_flag": "None"
        },
        {
          "ssid": "Bracket_Anchor_B",
          "bssid": "00:1A:2B:3C:4D:5F",
          "rssi": -56.48,
          "std_dev": 2.2,
          "anomaly_flag": "None"
        },
        {
          "ssid": "Bracket_Anchor_C",
          "bssid": "00:1A:2B:3C:4D:60",
          "rssi": -115,
          "std_dev": 3.75,
          "anomaly_flag": "SIGNAL_SHADOWING"
        }
      ]
    },
    {
      "point_id": "P12_08",
      "ground_truth_m": 1.17,
      "readings": [
        {
          "ssid": "Bracket_Anchor_A",
          "bssid": "00:1A:2B:3C:4D:5E",
          "rssi": -43.97,
          "std_dev": 2.1,
          "anomaly_flag": "None"
        },
        {
          "ssid": "Bracket_Anchor_B",
          "bssid": "00:1A:2B:3C:4D:5F",
          "rssi": -45.11,
          "std_dev": 1.87,
          "anomaly_flag": "None"
        },
        {
          "ssid": "Bracket_Anchor_C",
          "bssid": "00:1A:2B:3C:4D:60",
          "rssi": -43.46,
          "std_dev": 2.41,
          "anomaly_flag": "None"
        }
      ]
    },
    {
      "point_id": "P12_09",
      "ground_truth_m": 1.48,
      "readings": [
        {
          "ssid": "Bracket_Anchor_A",
          "bssid": "00:1A:2B:3C:4D:5E",
          "rssi": -47.13,
          "std_dev": 3.77,
          "anomaly_flag": "None"
        },
        {
          "ssid": "Bracket_Anchor_B",
          "bssid": "00:1A:2B:3C:4D:5F",
          "rssi": -44.25,
          "std_dev": 1.12,
          "anomaly_flag": "None"
        },
        {
          "ssid": "Bracket_Anchor_C",
          "bssid": "00:1A:2B:3C:4D:60",
          "rssi": -46.26,
          "std_dev": 0.63,
          "anomaly_flag": "None"
        }
      ]
    },
    {
      "point_id": "P12_10",
      "ground_truth_m": 2.89,
      "readings": [
        {
          "ssid": "Bracket_Anchor_A",
          "bssid": "00:1A:2B:3C:4D:5E",
          "rssi": -53.38,
          "std_dev": 1.02,
          "anomaly_flag": "None"
        },
        {
          "ssid": "Bracket_Anchor_B",
          "bssid": "00:1A:2B:3C:4D:5F",
          "rssi": -53.88,
          "std_dev": 1.66,
          "anomaly_flag": "None"
        },
        {
          "ssid": "Bracket_Anchor_C",
          "bssid": "00:1A:2B:3C:4D:60",
          "rssi": -115,
          "std_dev": 1.99,
          "anomaly_flag": "SIGNAL_SHADOWING"
        }
      ]
    },
    {
      "point_id": "P12_11",
      "ground_truth_m": 0.63,
      "readings": [
        {
          "ssid": "Bracket_Anchor_A",
          "bssid": "00:1A:2B:3C:4D:5E",
          "rssi": -36.38,
          "std_dev": 3.92,
          "anomaly_flag": "None"
        },
        {
          "ssid": "Bracket_Anchor_B",
          "bssid": "00:1A:2B:3C:4D:5F",
          "rssi": -115,
          "std_dev": 1.15,
          "anomaly_flag": "SIGNAL_SHADOWING"
        },
        {
          "ssid": "Bracket_Anchor_C",
          "bssid": "00:1A:2B:3C:4D:60",
          "rssi": -37.93,
          "std_dev": 0.72,
          "anomaly_flag": "None"
        }
      ]
    },
    {
      "point_id": "P12_12",
      "ground_truth_m": 3.31,
      "readings": [
        {
          "ssid": "Bracket_Anchor_A",
          "bssid": "00:1A:2B:3C:4D:5E",
          "rssi": -53.57,
          "std_dev": 2.52,
          "anomaly_flag": "None"
        },
        {
          "ssid": "Bracket_Anchor_B",
          "bssid": "00:1A:2B:3C:4D:5F",
          "rssi": -55.95,
          "std_dev": 1.55,
          "anomaly_flag": "None"
        },
        {
          "ssid": "Bracket_Anchor_C",
          "bssid": "00:1A:2B:3C:4D:60",
          "rssi": -56.29,
          "std_dev": 3.46,
          "anomaly_flag": "None"
        }
      ]
    }
  ]
}